dynamic_yaml/__init__.py
dynamic_yaml/yaml_wrappers.py
dynamic_yaml-2.0.0.dist-info/LICENSE.txt
dynamic_yaml-2.0.0.dist-info/METADATA
dynamic_yaml-2.0.0.dist-info/WHEEL
dynamic_yaml-2.0.0.dist-info/top_level.txt
dynamic_yaml-2.0.0.dist-info/RECORD
