Metadata-Version: 2.1
Name: dynamic-yaml
Version: 2.0.0
Summary: Enables self referential yaml entries
Author-email: "Liam H. Childs" <liam.h.childs@gmail.com>
License: MIT License
Project-URL: Homepage, https://github.com/childsish/dynamic-yaml
Keywords: yaml,configuration
Classifier: License :: OSI Approved :: MIT License
Classifier: Programming Language :: Python
Classifier: Programming Language :: Python :: 3
Requires-Python: >=3.0
License-File: LICENSE.txt
Requires-Dist: pyyaml>=5.4
